{"ip":"188.127.241.222","port":25601,"debug":{"ping":false,"query":true,"bedrock":false,"srv":false,"querymismatch":false,"ipinsrv":false,"cnameinsrv":false,"animatedmotd":false,"cachehit":false,"cachetime":1783780873,"cacheexpire":1783781173,"apiversion":2,"error":{"ping":"Unknown problem with returned server data."}},"motd":{"raw":["proxy mc.cooldmc.ru"],"clean":["proxy mc.cooldmc.ru"],"html":["proxy mc.cooldmc.ru"]},"players":{"online":0,"max":67},"version":"1.21.11","online":true,"software":"Paper on 1.21.11-R0.1-SNAPSHOT","map":"world","plugins":{"names":["AdvancedRestart","ArmorPoser","AttackIndicator","BlueMap","ChatCM","Chunky","CommandAPI","CompassCM","CoreProtect","craftableinvframes","CustomDiscs","CustomF3Brand","CustomPrefixCM","floodgate","GSit","HeadsPluginAPI","InvSeePlusPlus","ItemRenamerReloaded","LuckPerms","MessagesOnHead","MinerTrack","MyCommand","packetevents","PandaNotes","PaperAttributeSwapFix","PatPatPlugin","PlaceholderAPI","PlugManX","ProtocolLib","SimpleVoiceChatAdmin","SkinsRestorer","StaffWorkCM","TAB","Vault","VClansCM","ViaBackwards","ViaVersion","voicechat"],"raw":["AdvancedRestart 1.2.1","ArmorPoser 1.4.0","AttackIndicator 2.4","BlueMap 5.16","ChatCM 1.2","Chunky 1.4.40","CommandAPI 11.2.0","CompassCM 3.1","CoreProtect 23.2","craftableinvframes 2.3.3","CustomDiscs 2.6.0","CustomF3Brand 1.2.1","CustomPrefixCM 1.0","floodgate 2.2.5-SNAPSHOT (b132-5a72b6a)","GSit 3.5.1","HeadsPluginAPI 3.4.2","InvSeePlusPlus 0.31.15","ItemRenamerReloaded 1.6","LuckPerms 5.5.59","MessagesOnHead 1.6","MinerTrack 1.10.1.1","MyCommand 5.7.4","packetevents 2.13.0","PandaNotes 1.0-SNAPSHOT","PaperAttributeSwapFix 1.1.0","PatPatPlugin 1.2.5+0268419","PlaceholderAPI 2.12.3","PlugManX 3.0.4","ProtocolLib 5.4.0","SimpleVoiceChatAdmin 1.3","SkinsRestorer 15.12.4","StaffWorkCM 1.1","TAB 6.1.0","Vault 2.20.2","VClansCM 1.0-beta-4","ViaBackwards 5.10.0","ViaVersion 5.10.0","voicechat 2.6.20"]},"eula_blocked":false}